<?xml version="1.0" encoding="ISO-8859-1"?>
<objects>
	<actors>
		<node>
			<name>Actor1</name>
			<label>Romeo</label>
			<state frame="0">
				<pos>0.7f 0.0f 0.7f 0.0f 0.0f 1.0f 0.0f 0.0f 0.7f 0.0f -0.7f 0.0f 100.0f 000.0f -100.0f 1f</pos>
			</state>
			<state frame="560">
				<pos>0.7f 0.0f 0.7f 0.0f 0.0f 1.0f 0.0f 0.0f 0.7f 0.0f -0.7f 0.0f 100.0f 000.0f -100.0f 1f</pos>
			</state>
			<state frame="8970">
				<pos>0.7f 0.0f 0.7f 0.0f 0.0f 1.0f 0.0f 0.0f 0.7f 0.0f -0.7f 0.0f 100.0f 000.0f -100.0f 1f</pos>
			</state>
		</node>
	</actors>

	<lights>
		<node>
			<name>Light1</name>
			<label>Dramatic Stairwell</label>
			<state frame="56" on="true">
				<pos>0.7f 0.0f 0.7f 0.0f 0.0f 1.0f 0.0f 0.0f 0.7f 0.0f -0.7f 0.0f 100.0f 000.0f -100.0f 1f</pos>
			</state>
			<state frame="139" on="true">
				<pos>0.2f 0.0f 0.5f 0.0f 0.0f 1.0f 0.0f 0.0f 0.7f 0.0f -0.7f 0.0f 100.0f 000.0f -100.0f 1f</pos> 
			</state>
		</node>
	</lights>

	<events>
		<node>
			<label>Run to door</label>
			<duration start="0" end="34" />
			<relevence>3</relevence>
			<actors>
				<name>Actor1</name>
				<name>Actor2</name>
			</actors>
		</node>
	</events>
	
	<cameras>
		<node>
			<name>Camera1</name>
			<state frame="0">
				<pos>0.7f 0.0f 0.7f 0.0f 0.0f 1.0f 0.0f 0.0f 0.7f 0.0f -0.7f 0.0f 100.0f 000.0f -100.0f 1f</pos>
			</state>
		</node>
	</cameras>
</objects>